{
    "backend": "api-server-nodejs",
    "db_name": "",
    "db_pass": "",
    "db_type": "sqlite",
    "db_user": "",
    "dbms": "1",
    "description": "generated product",
    "design": "horizon-ui",
    "docker": "1",
    "err_code": 0,
    "frontend": "react",
    "heroku": "0",
    "pattern": "fullstack",
    "pro": "0",
    "task_id": "17669dec-bc50-4dfd-945f-ff388713d538",
    "task_info": "Upload Sources [0%] - 185 files",
    "task_output": "17669dec-bc50-4dfd-945f-ff388713d538.zip",
    "task_result": "SUCCESS",
    "task_state": "RUNNING",
    "task_ts_end": "2023-06-27-09-55-29",
    "task_ts_start": "2023-06-27-09-55-28"
}